{
  "records": [
    {
      "speciesId": "panthera_leo",
      "gbifTaxonKey": 8142092,
      "summaries": [
        {
          "region": "Africa",
          "occurrenceCount": 4918
        }
      ]
    },
    {
      "speciesId": "loxodonta_africana",
      "gbifTaxonKey": 7924776,
      "summaries": [
        {
          "region": "Africa",
          "occurrenceCount": 2342
        }
      ]
    },
    {
      "speciesId": "canis_lupus",
      "gbifTaxonKey": 6758903,
      "summaries": [
        {
          "region": "North America",
          "occurrenceCount": 465
        }
      ]
    },
    {
      "speciesId": "odocoileus_virginianus",
      "gbifTaxonKey": 659046,
      "summaries": [
        {
          "region": "North America",
          "occurrenceCount": 4709
        }
      ]
    },
    {
      "speciesId": "balaenoptera_musculus",
      "gbifTaxonKey": 419427,
      "summaries": [
        {
          "region": "Global oceans",
          "occurrenceCount": 125
        }
      ]
    },
    {
      "speciesId": "ursus_americanus",
      "gbifTaxonKey": 2866111,
      "summaries": [
        {
          "region": "North America",
          "occurrenceCount": 4005
        }
      ]
    },
    {
      "speciesId": "castor_canadensis",
      "gbifTaxonKey": 2709881,
      "summaries": [
        {
          "region": "North America",
          "occurrenceCount": 4287
        }
      ]
    },
    {
      "speciesId": "lontra_canadensis",
      "gbifTaxonKey": 9194662,
      "summaries": [
        {
          "region": "North America",
          "occurrenceCount": 1992
        }
      ]
    },
    {
      "speciesId": "phoca_vitulina",
      "gbifTaxonKey": 7260742,
      "summaries": [
        {
          "region": "North Atlantic",
          "occurrenceCount": 2177
        }
      ]
    },
    {
      "speciesId": "equus_caballus_ferus",
      "gbifTaxonKey": 7534638,
      "summaries": [
        {
          "region": "Asia",
          "occurrenceCount": 3550
        }
      ]
    }
  ]
}